keyterms/__about__.py
keyterms/__init__.py
keyterms/plugin.py
keyterms/patches/caddyfile
keyterms/patches/k8s-deployments
keyterms/patches/k8s-jobs
keyterms/patches/k8s-services
keyterms/patches/local-docker-compose-dev-services
keyterms/patches/local-docker-compose-jobs-services
keyterms/patches/local-docker-compose-services
keyterms/patches/openedx-cms-common-settings
keyterms/patches/openedx-lms-common-settings
keyterms/templates/keyterms/apps/settings/tutor.py
keyterms/templates/keyterms/build/keyterms/Dockerfile
keyterms/templates/keyterms/hooks/keyterms/init
keyterms/templates/keyterms/hooks/lms/init
keyterms/templates/keyterms/hooks/mysql/init
tutor_keyterms_api-0.1.1.dist-info/METADATA
tutor_keyterms_api-0.1.1.dist-info/WHEEL
tutor_keyterms_api-0.1.1.dist-info/entry_points.txt
tutor_keyterms_api-0.1.1.dist-info/top_level.txt
tutor_keyterms_api-0.1.1.dist-info/RECORD
