Metadata-Version: 2.1
Name: tutor-keyterms-api
Version: 0.1.1
Summary: keyterms plugin for Tutor
Home-page: https://github.com/CUCWD/tutor-keyterms-api
Author: CUCWD
Project-URL: Code, https://github.com/CUCWD/edx_key_terms_api
Project-URL: Issue tracker, https://github.com/CUCWD/edx_key_terms_api/issues
Classifier: Development Status :: 3 - Alpha
Classifier: Intended Audience :: Developers
Classifier: License :: OSI Approved :: GNU Affero General Public License v3
Classifier: Operating System :: OS Independent
Classifier: Programming Language :: Python
Classifier: Programming Language :: Python :: 3.6
Classifier: Programming Language :: Python :: 3.7
Classifier: Programming Language :: Python :: 3.8
Classifier: Programming Language :: Python :: 3.9
Classifier: Programming Language :: Python :: 3.10
Requires-Python: >=3.6
Requires-Dist: tutor
